fastbruno/__init__.py
fastbruno/__internal/brunofy.py
fastbruno/__internal/brunotypes.py
fastbruno/__internal/fastapi.py
fastbruno/__internal/fastapiinfo.py
fastbruno/__internal/fastbruno.py
fastbruno/__internal/logger.py
fastbruno/__version__.py
fastbruno/cli.py
fastbruno-0.1.5.dist-info/entry_points.txt
fastbruno-0.1.5.dist-info/METADATA
fastbruno-0.1.5.dist-info/WHEEL
fastbruno-0.1.5.dist-info/RECORD
