Metadata-Version: 2.1
Name: fastbruno
Version: 0.1.5
Summary: A FastAPI extension package to generate Bruno API documentation
Author: Nahid Hasan
Author-email: nahidhasan282@gmail.com
Requires-Python: >=3.9,<4.0
Classifier: Programming Language :: Python :: 3
Classifier: Programming Language :: Python :: 3.9
Classifier: Programming Language :: Python :: 3.10
Classifier: Programming Language :: Python :: 3.11
Classifier: Programming Language :: Python :: 3.12
Classifier: Programming Language :: Python :: 3.13
